copula_scengen/__init__.py
copula_scengen/main.py
copula_scengen/modules/copula/__init__.py
copula_scengen/modules/copula/copula_sample.py
copula_scengen/modules/copula/copula_sample2d.py
copula_scengen/modules/copula/empirical_copula.py
copula_scengen/modules/copula/empirical_extension_copula2d.py
copula_scengen/modules/functions/__init__.py
copula_scengen/modules/functions/base.py
copula_scengen/modules/functions/empirical_distribution_function.py
copula_scengen/modules/functions/empirical_joint_distribution_function.py
copula_scengen/modules/functions/extended_empirical_quantile_function.py
copula_scengen/modules/functions/step_function.py
copula_scengen/modules/functions/uniform_distribution_function.py
copula_scengen/modules/generator/__init__.py
copula_scengen/modules/generator/copula_sample_generator.py
copula_scengen/modules/generator/copula_sample_transformer.py
copula_scengen/modules/generator/deviation_cache.py
copula_scengen/modules/generator/scenario_generator.py
copula_scengen/modules/utils/__init__.py
copula_scengen/modules/utils/cdf.py
copula_scengen/modules/utils/margin_type.py
copula_scengen/schemas/__init__.py
copula_scengen/schemas/margin_type.py
copula_scengen-0.1.0.dist-info/METADATA
copula_scengen-0.1.0.dist-info/WHEEL
copula_scengen-0.1.0.dist-info/licenses/LICENSE
copula_scengen-0.1.0.dist-info/RECORD
