Metadata-Version: 2.4
Name: copula-scengen
Version: 0.1.0
Summary: Package implementing a scenario generation method based on copulas
Project-URL: Homepage, https://github.com/ondrakomora/copula-scengen
Project-URL: Issues, https://github.com/ondrakomora/copula-scengen/issues
Author-email: Ondrej Komora <ondrakomora@gmail.com>
License-Expression: MIT
License-File: LICENSE
Requires-Python: >=3.10
Requires-Dist: loguru==0.7.3
Requires-Dist: pandas==2.3.3
Requires-Dist: pydantic==2.9.0
